fluidprop.py
rbc.py
fluidprop-1.2.0.dist-info/AUTHORS.rst
fluidprop-1.2.0.dist-info/LICENSE.txt
fluidprop-1.2.0.dist-info/METADATA
fluidprop-1.2.0.dist-info/WHEEL
fluidprop-1.2.0.dist-info/top_level.txt
fluidprop-1.2.0.dist-info/RECORD
