Metadata-Version: 2.1
Name: fluidprop
Version: 1.2.0
Summary: Easy access to thermodynamic fluid properties as a function of temperature and pressure. With a minimal command-line interface.
Home-page: https://github.com/Dennis-van-Gils/python-fluidprop/
Author: Dennis van Gils
Author-email: vangils.dennis@gmail.com
License: MIT
Project-URL: Issue Tracker, https://github.com/Dennis-van-Gils/python-fluidprop/issues
Keywords: CoolProp,fluids,thermodynamic
Classifier: Development Status :: 5 - Production/Stable
Classifier: Intended Audience :: Developers
Classifier: License :: OSI Approved :: MIT License
Classifier: Operating System :: OS Independent
Classifier: Programming Language :: Python
Classifier: Programming Language :: Python :: 3
Classifier: Programming Language :: Python :: 3.9
Classifier: Programming Language :: Python :: 3.10
Classifier: Programming Language :: Python :: 3.11
Classifier: Programming Language :: Python :: 3.12
Classifier: Topic :: Utilities
Requires-Python: >=3.9
License-File: LICENSE.txt
License-File: AUTHORS.rst
Requires-Dist: CoolProp ~=6.6
Requires-Dist: numpy ~=1.25
